gfs_network/__init__.py
gfs_network/feature_selection_network.py
gfs_network/select_gumbel_features.py
gfs_network/sklearn_interface.py
gfs_network-0.3.1.dist-info/LICENSE
gfs_network-0.3.1.dist-info/METADATA
gfs_network-0.3.1.dist-info/WHEEL
gfs_network-0.3.1.dist-info/RECORD
