Metadata-Version: 2.1
Name: gfs_network
Version: 0.3.1
Summary: An end-to-end feature selection distribution with ~constant runtime(number of features) complexity.
Home-page: https://github.com/wwydmanski/GFSNetwork
License: MIT
Author: Witold Wydmański
Author-email: wwydmanski@gmail.com
Requires-Python: >=3.9,<4.0
Classifier: License :: OSI Approved :: MIT License
Classifier: Programming Language :: Python :: 3
Classifier: Programming Language :: Python :: 3.9
Classifier: Programming Language :: Python :: 3.10
Classifier: Programming Language :: Python :: 3.11
Classifier: Programming Language :: Python :: 3.12
Requires-Dist: torch (>=2.0,<3.0)
Requires-Dist: tqdm (>=4.65,<5.0)
Project-URL: Repository, https://github.com/wwydmanski/GFSNetwork
